LICENCE
MANIFEST.in
README.md
setup.py
python_uime.egg-info/PKG-INFO
python_uime.egg-info/SOURCES.txt
python_uime.egg-info/dependency_links.txt
python_uime.egg-info/requires.txt
python_uime.egg-info/top_level.txt
uime/__init__.py
uime/decorator.py
uime/server.py
uime/static/css/uime.css
uime/static/css/uime.min.css
uime/static/js/uime.js
uime/static/js/uime.min.js
uime/templates/index.html