Metadata-Version: 2.4
Name: python-uime
Version: 1.1.0
Summary: A python library to help you build simple UI forms for your python functions
Home-page: https://github.com/livetheoogway/python-uime
Author: Tushar Naik
Author-email: tushar.knaik@gmail.com
License:  License 2.0
Keywords: ui,generate-ui,ui-generate,ui-enable,function to ui,flask style,decorator,tushar
Classifier: Development Status :: 5 - Production/Stable
Classifier: Intended Audience :: Developers
Classifier: License :: OSI Approved :: Apache Software License
Classifier: Operating System :: OS Independent
Classifier: Programming Language :: Python :: 3.12
Classifier: Programming Language :: Python :: Implementation :: PyPy
Classifier: Topic :: Utilities
Classifier: Topic :: System :: Networking
Classifier: Topic :: System :: Distributed Computing
License-File: LICENCE
Requires-Dist: Flask>=1.1.2
Dynamic: author
Dynamic: author-email
Dynamic: classifier
Dynamic: description
Dynamic: description-content-type
Dynamic: home-page
Dynamic: keywords
Dynamic: license
Dynamic: license-file
Dynamic: requires-dist
Dynamic: summary
